README.rst
setup.py
Flask_Responses.egg-info/PKG-INFO
Flask_Responses.egg-info/SOURCES.txt
Flask_Responses.egg-info/dependency_links.txt
Flask_Responses.egg-info/not-zip-safe
Flask_Responses.egg-info/requires.txt
Flask_Responses.egg-info/top_level.txt
flask_responses/__init__.py
flask_responses/responses.py
flask_responses/utility.py